normPlot/__init__.py
normPlot/fittingFuncs2.py
normPlot/guiControls2.py
normPlot/guiMainWin2.py
normPlot/normPlot2.py
normplot-2.5.0.dist-info/licenses/LICENSE
normplot-2.5.0.dist-info/METADATA
normplot-2.5.0.dist-info/WHEEL
normplot-2.5.0.dist-info/entry_points.txt
normplot-2.5.0.dist-info/top_level.txt
normplot-2.5.0.dist-info/RECORD
