Metadata-Version: 2.4
Name: normPlot
Version: 2.5.0
Summary: An interactive tool for normalizing stellar spectra
Author-email: Colin Folsom <fosomcp+dev@gmail.com>
License-Expression: MIT
Project-URL: Homepage, https://github.com/folsomcp/normPlot/
Project-URL: Documentation, https://folsomcp.github.io/specpolFlow/
Classifier: Development Status :: 5 - Production/Stable
Classifier: Intended Audience :: Science/Research
Classifier: Topic :: Scientific/Engineering :: Astronomy
Classifier: Programming Language :: Python :: 3
Requires-Python: >=3.8
License-File: LICENSE
Requires-Dist: numpy
Requires-Dist: scipy
Requires-Dist: matplotlib
Dynamic: license-file
